[
	{
		"Car Name": "AM General Hummer SUV 2000",
		"Image": "07684.jpg",
		"Fuel Type": "Diesel",
		"Fuel Tank Capacity": 159,
		"Seating Capacity": "2 to 4",
		"Body Type": "Convertible",
		"Transmission Type": "Automatic"
	},
	{
		"Car Name": "Acura Integra Type R 2001",
		"Image": "00198.jpg",
		"Fuel Type": "Petrol",
		"Fuel Tank Capacity": 50,
		"Seating Capacity": 5,
		"Body Type": "No information",
		"Transmission Type": "Manual"
	},
	{
		"Car Name": "Acura RL Sedan 2012",
		"Image": "01034.jpg",
		"Fuel Type": "Gas",
		"Fuel Tank Capacity": 74,
		"Seating Capacity": 5,
		"Body Type": "Sedan",
		"Transmission Type": "Automatic"
	},
	{
		"Car Name": "Acura TL Sedan 2012",
		"Image": "06974.jpg",
		"Fuel Type": "Gas",
		"Fuel Tank Capacity": 70,
		"Seating Capacity": 5,
		"Body Type": "Sedan",
		"Transmission Type": "Automatic"
	},
	{
		"Car Name": "Acura TL Type-S 2008",
		"Image": "03238.jpg",
		"Fuel Type": "Gas",
		"Fuel Tank Capacity": 65,
		"Seating Capacity": 5,
		"Body Type": "Sedan",
		"Transmission Type": "Manual"
	},
	{
		"Car Name": "Acura TSX Sedan 2012",
		"Image": "04484.jpg",
		"Fuel Type": "Gas",
		"Fuel Tank Capacity": 70,
		"Seating Capacity": 5,
		"Body Type": "Sedan",
		"Transmission Type": "Automatic"
	},
	{
		"Car Name": "Acura ZDX Hatchback 2012",
		"Image": "01105.jpg",
		"Fuel Type": "Gas",
		"Fuel Tank Capacity": 80,
		"Seating Capacity": 5,
		"Body Type": "Hatchback",
		"Transmission Type": "Automatic"
	},
	{
		"Car Name": "Aston Martin V8 Vantage Convertible 2012",
		"Image": "04186.jpg",
		"Fuel Type": "Gas",
		"Fuel Tank Capacity": 80,
		"Seating Capacity": 2,
		"Body Type": "Convertible",
		"Transmission Type": "Automatic/Manual"
	},
	{
		"Car Name": "Aston Martin V8 Vantage Coupe 2012",
		"Image": "00503.jpg",
		"Fuel Type": "Petrol/Gas",
		"Fuel Tank Capacity": 80,
		"Seating Capacity": 2,
		"Body Type": "Coupe",
		"Transmission Type": "Manual"
	},
	{
		"Car Name": "Aston Martin Virage Convertible 2012",
		"Image": "05366.jpg",
		"Fuel Type": "Gas",
		"Fuel Tank Capacity": 78,
		"Seating Capacity": 4,
		"Body Type": "Convertible",
		"Transmission Type": "Automatic"
	},
	{
		"Car Name": "Aston Martin Virage Coupe 2012",
		"Image": "03208.jpg",
		"Fuel Type": "Gas",
		"Fuel Tank Capacity": 78,
		"Seating Capacity": 4,
		"Body Type": "Coupe",
		"Transmission Type": "Automatic"
	},
	{
		"Car Name": "Audi 100 Sedan 1994",
		"Image": "02887.jpg",
		"Fuel Type": "Gas",
		"Fuel Tank Capacity": 80,
		"Seating Capacity": 5,
		"Body Type": "Sedan",
		"Transmission Type": "Manual/Automatic"
	},
	{
		"Car Name": "Audi 100 Wagon 1994",
		"Image": "03435.jpg",
		"Fuel Type": "Gas",
		"Fuel Tank Capacity": 80,
		"Seating Capacity": 5,
		"Body Type": "Sedan",
		"Transmission Type": "Automatic"
	},
	{
		"Car Name": "Audi A5 Coupe 2012",
		"Image": "07976.jpg",
		"Fuel Type": "Gas",
		"Fuel Tank Capacity": 64,
		"Seating Capacity": 4,
		"Body Type": "Coupe",
		"Transmission Type": "Manual"
	},
	{
		"Car Name": "Audi R8 Coupe 2012",
		"Image": "03139.jpg",
		"Fuel Type": "Gas",
		"Fuel Tank Capacity": 90,
		"Seating Capacity": 2,
		"Body Type": "Coupe",
		"Transmission Type": "Manual"
	},
	{
		"Car Name": "Audi RS 4 Convertible 2008",
		"Image": "04497.jpg",
		"Fuel Type": "Gas",
		"Fuel Tank Capacity": 63,
		"Seating Capacity": 4,
		"Body Type": "Convertible",
		"Transmission Type": "Manual"
	},
	{
		"Car Name": "Audi S4 Sedan 2007",
		"Image": "06565.jpg",
		"Fuel Type": "nill",
		"Fuel Tank Capacity": 63,
		"Seating Capacity": 5,
		"Body Type": "Sedan",
		"Transmission Type": "Manual"
	},
	{
		"Car Name": "Audi S4 Sedan 2012",
		"Image": "01848.jpg",
		"Fuel Type": "Petrol/Gas",
		"Fuel Tank Capacity": 64,
		"Seating Capacity": 5,
		"Body Type": "Sedan",
		"Transmission Type": "Automatic/Manual"
	},
	{
		"Car Name": "Audi S5 Convertible 2012",
		"Image": "05482.jpg",
		"Fuel Type": "Gas",
		"Fuel Tank Capacity": 64,
		"Seating Capacity": 5,
		"Body Type": "Convertible",
		"Transmission Type": "Automatic/Manual"
	},
	{
		"Car Name": "Audi S5 Coupe 2012",
		"Image": "06581.jpg",
		"Fuel Type": "Gas",
		"Fuel Tank Capacity": 64,
		"Seating Capacity": 4,
		"Body Type": "Coupe",
		"Transmission Type": "Automatic"
	},
	{
		"Car Name": "Audi S6 Sedan 2011",
		"Image": "00772.jpg",
		"Fuel Type": "Gas",
		"Fuel Tank Capacity": 80,
		"Seating Capacity": 5,
		"Body Type": "Sedan",
		"Transmission Type": "Automatic"
	},
	{
		"Car Name": "Audi TT Hatchback 2011",
		"Image": "00723.jpg",
		"Fuel Type": "Gas",
		"Fuel Tank Capacity": 15.9,
		"Seating Capacity": 4,
		"Body Type": "Hatchback",
		"Transmission Type": "Manual"
	},
	{
		"Car Name": "Audi TT RS Coupe 2012",
		"Image": "03019.jpg",
		"Fuel Type": "Gas",
		"Fuel Tank Capacity": 60,
		"Seating Capacity": 4,
		"Body Type": "Coupe",
		"Transmission Type": "Manual"
	},
	{
		"Car Name": "Audi TTS Coupe 2012",
		"Image": "00017.jpg",
		"Fuel Type": "Gas",
		"Fuel Tank Capacity": 60,
		"Seating Capacity": 4,
		"Body Type": "Coupe",
		"Transmission Type": "Manual"
	},
	{
		"Car Name": "Audi V8 Sedan 1994",
		"Image": "02304.jpg",
		"Fuel Type": "Gas",
		"Fuel Tank Capacity": 80,
		"Seating Capacity": 5,
		"Body Type": "Sedan",
		"Transmission Type": "Automatic"
	},
	{
		"Car Name": "BMW 1 Series Convertible 2012",
		"Image": "07524.jpg",
		"Fuel Type": "Gas",
		"Fuel Tank Capacity": 53,
		"Seating Capacity": 4,
		"Body Type": "Convertible",
		"Transmission Type": "Manual"
	},
	{
		"Car Name": "BMW 1 Series Coupe 2012",
		"Image": "02772.jpg",
		"Fuel Type": "Diesel",
		"Fuel Tank Capacity": 51,
		"Seating Capacity": 4,
		"Body Type": "Coupe",
		"Transmission Type": "Manual/Automatic"
	},
	{
		"Car Name": "BMW 3 Series Sedan 2012",
		"Image": "07841.jpg",
		"Fuel Type": "Petrol/Diesel",
		"Fuel Tank Capacity": 60,
		"Seating Capacity": 5,
		"Body Type": "Sedan",
		"Transmission Type": "Automatic"
	},
	{
		"Car Name": "BMW 3 Series Wagon 2012",
		"Image": "02087.jpg",
		"Fuel Type": "Gas",
		"Fuel Tank Capacity": 60,
		"Seating Capacity": 5,
		"Body Type": "Wagon",
		"Transmission Type": "Manual"
	},
	{
		"Car Name": "BMW 6 Series Convertible 2007",
		"Image": "03716.jpg",
		"Fuel Type": "Gas",
		"Fuel Tank Capacity": 70,
		"Seating Capacity": 4,
		"Body Type": "Convertible",
		"Transmission Type": "Manual"
	},
	{
		"Car Name": "BMW ActiveHybrid 5 Sedan 2012",
		"Image": "04089.jpg",
		"Fuel Type": "Petrol",
		"Fuel Tank Capacity": 67,
		"Seating Capacity": 5,
		"Body Type": "Sedan",
		"Transmission Type": "Automatic"
	},
	{
		"Car Name": "BMW M3 Coupe 2012",
		"Image": "04760.jpg",
		"Fuel Type": "Gas",
		"Fuel Tank Capacity": 63,
		"Seating Capacity": 4,
		"Body Type": "Coupe",
		"Transmission Type": "Manual"
	},
	{
		"Car Name": "BMW M5 Sedan 2010",
		"Image": "00792.jpg",
		"Fuel Type": "Gas",
		"Fuel Tank Capacity": 70,
		"Seating Capacity": 5,
		"Body Type": "Sedan",
		"Transmission Type": "Automatic"
	},
	{
		"Car Name": "BMW M6 Convertible 2010",
		"Image": "02774.jpg",
		"Fuel Type": "Gas",
		"Fuel Tank Capacity": 70,
		"Seating Capacity": 4,
		"Body Type": "Convertible",
		"Transmission Type": "Automatic"
	},
	{
		"Car Name": "BMW X3 SUV 2012",
		"Image": "06997.jpg",
		"Fuel Type": "Petrol",
		"Fuel Tank Capacity": 67,
		"Seating Capacity": 5,
		"Body Type": "SUV",
		"Transmission Type": "Automatic"
	},
	{
		"Car Name": "BMW X5 SUV 2007",
		"Image": "06559.jpg",
		"Fuel Type": "Diesel",
		"Fuel Tank Capacity": 85,
		"Seating Capacity": 5,
		"Body Type": "SUV",
		"Transmission Type": "Automatic"
	},
	{
		"Car Name": "BMW X6 SUV 2012",
		"Image": "05685.jpg",
		"Fuel Type": "Petrol",
		"Fuel Tank Capacity": 85,
		"Seating Capacity": 4,
		"Body Type": "SUV",
		"Transmission Type": "Automatic"
	},
	{
		"Car Name": "BMW Z4 Convertible 2012",
		"Image": "07709.jpg",
		"Fuel Type": "Gas",
		"Fuel Tank Capacity": 55,
		"Seating Capacity": 2,
		"Body Type": "Convertible",
		"Transmission Type": "Manual"
	},
	{
		"Car Name": "Bentley Arnage Sedan 2009",
		"Image": "01284.jpg",
		"Fuel Type": "Petrol",
		"Fuel Tank Capacity": 96,
		"Seating Capacity": 5,
		"Body Type": "Sedan",
		"Transmission Type": "Automatic"
	},
	{
		"Car Name": "Bentley Continental Flying Spur Sedan 2007",
		"Image": "02231.jpg",
		"Fuel Type": "Gas",
		"Fuel Tank Capacity": 90,
		"Seating Capacity": 5,
		"Body Type": "Sedan",
		"Transmission Type": "Automatic"
	},
	{
		"Car Name": "Bentley Continental GT Coupe 2007",
		"Image": "04449.jpg",
		"Fuel Type": "Gas",
		"Fuel Tank Capacity": 90,
		"Seating Capacity": 5,
		"Body Type": "Coupe",
		"Transmission Type": "Automatic"
	},
	{
		"Car Name": "Bentley Continental GT Coupe 2012",
		"Image": "01401.jpg",
		"Fuel Type": "Gas",
		"Fuel Tank Capacity": 87,
		"Seating Capacity": 4,
		"Body Type": "Coupe",
		"Transmission Type": "Automatic"
	},
	{
		"Car Name": "Bentley Continental Supersports Conv. Convertible 2012",
		"Image": "05310.jpg",
		"Fuel Type": "Gas",
		"Fuel Tank Capacity": 90,
		"Seating Capacity": 4,
		"Body Type": "Convertible",
		"Transmission Type": "Automatic"
	},
	{
		"Car Name": "Bentley Mulsanne Sedan 2011",
		"Image": "02718.jpg",
		"Fuel Type": "Gas",
		"Fuel Tank Capacity": 96,
		"Seating Capacity": 4,
		"Body Type": "Sedan",
		"Transmission Type": "Automatic"
	},
	{
		"Car Name": "Bugatti Veyron 16.4 Convertible 2009",
		"Image": "05203.jpg",
		"Fuel Type": "Gas",
		"Fuel Tank Capacity": 100,
		"Seating Capacity": 2,
		"Body Type": "Convertible",
		"Transmission Type": "Automatic"
	},
	{
		"Car Name": "Bugatti Veyron 16.4 Coupe 2009",
		"Image": "07635.jpg",
		"Fuel Type": "Gas",
		"Fuel Tank Capacity": 100,
		"Seating Capacity": 2,
		"Body Type": "Coupe",
		"Transmission Type": "Automatic"
	},
	{
		"Car Name": "Buick Enclave SUV 2012",
		"Image": "05997.jpg",
		"Fuel Type": "Gas",
		"Fuel Tank Capacity": 83,
		"Seating Capacity": 7,
		"Body Type": "SUV",
		"Transmission Type": "Automatic"
	},
	{
		"Car Name": "Buick Rainier SUV 2007",
		"Image": "00193.jpg",
		"Fuel Type": "Gas",
		"Fuel Tank Capacity": 83,
		"Seating Capacity": 5,
		"Body Type": "SUV",
		"Transmission Type": "Automatic"
	},
	{
		"Car Name": "Buick Regal GS 2012",
		"Image": "02988.jpg",
		"Fuel Type": "Gas",
		"Fuel Tank Capacity": 70,
		"Seating Capacity": 5,
		"Body Type": "Sedan",
		"Transmission Type": "Manual"
	},
	{
		"Car Name": "Buick Verano Sedan 2012",
		"Image": "04366.jpg",
		"Fuel Type": "Gas",
		"Fuel Tank Capacity": 58,
		"Seating Capacity": 5,
		"Body Type": "Sedan",
		"Transmission Type": "Automatic"
	},
	{
		"Car Name": "Cadillac CTS-V Sedan 2012",
		"Image": "07086.jpg",
		"Fuel Type": "Gas",
		"Fuel Tank Capacity": 68,
		"Seating Capacity": 5,
		"Body Type": "Sedan",
		"Transmission Type": "Automatic"
	},
	{
		"Car Name": "Cadillac Escalade EXT Crew Cab 2007",
		"Image": "06566.jpg",
		"Fuel Type": "Gas",
		"Fuel Tank Capacity": 117,
		"Seating Capacity": 5,
		"Body Type": "Crew Cab",
		"Transmission Type": "Automatic"
	},
	{
		"Car Name": "Cadillac SRX SUV 2012",
		"Image": "00866.jpg",
		"Fuel Type": "Gas",
		"Fuel Tank Capacity": 80,
		"Seating Capacity": 5,
		"Body Type": "SUV",
		"Transmission Type": "Automatic"
	},
	{
		"Car Name": "Chevrolet Avalanche Crew Cab 2012",
		"Image": "05639.jpg",
		"Fuel Type": "Gas",
		"Fuel Tank Capacity": 117,
		"Seating Capacity": 5,
		"Body Type": "Crew Cab",
		"Transmission Type": "Automatic"
	},
	{
		"Car Name": "Chevrolet Beat",
		"Image": "chevrolet_beat.jpg",
		"Fuel Type": "Petrol",
		"Fuel Tank Capacity": 35,
		"Seating Capacity": 5,
		"Body Type": "Hatchback",
		"Transmission Type": "Manual"
	},
	{
		"Car Name": "Chevrolet Camaro Convertible 2012",
		"Image": "00607.jpg",
		"Fuel Type": "Gas",
		"Fuel Tank Capacity": 71,
		"Seating Capacity": 4,
		"Body Type": "Convertible",
		"Transmission Type": "Manual"
	},
	{
		"Car Name": "Chevrolet Cobalt SS 2010",
		"Image": "04452.jpg",
		"Fuel Type": "Gas",
		"Fuel Tank Capacity": 49,
		"Seating Capacity": 4,
		"Body Type": "Sedan",
		"Transmission Type": "Manual"
	},
	{
		"Car Name": "Chevrolet Corvette Convertible 2012",
		"Image": "00738.jpg",
		"Fuel Type": "Gas",
		"Fuel Tank Capacity": 68,
		"Seating Capacity": 2,
		"Body Type": "Convertible",
		"Transmission Type": "Manual"
	},
	{
		"Car Name": "Chevrolet Corvette Ron Fellows Edition Z06 2007",
		"Image": "04437.jpg",
		"Fuel Type": "Gas",
		"Fuel Tank Capacity": 68,
		"Seating Capacity": 2,
		"Body Type": "Ron Fellow",
		"Transmission Type": "Manual"
	},
	{
		"Car Name": "Chevrolet Corvette ZR1 2012",
		"Image": "02994.jpg",
		"Fuel Type": "Gas",
		"Fuel Tank Capacity": 68,
		"Seating Capacity": 2,
		"Body Type": "Hatchback",
		"Transmission Type": "Manual"
	},
	{
		"Car Name": "Chevrolet Cruze",
		"Image": "chevrolet_cruze.jpg",
		"Fuel Type": "Diesel",
		"Fuel Tank Capacity": 60,
		"Seating Capacity": 5,
		"Body Type": "Sedan",
		"Transmission Type": "Manual"
	},
	{
		"Car Name": "Chevrolet Enjoy",
		"Image": "chevrolet_enjoy.jpg",
		"Fuel Type": "Petrol",
		"Fuel Tank Capacity": 50,
		"Seating Capacity": 7,
		"Body Type": "MUV",
		"Transmission Type": "Manual"
	},
	{
		"Car Name": "Chevrolet Express Cargo Van 2007",
		"Image": "04189.jpg",
		"Fuel Type": "Gas",
		"Fuel Tank Capacity": 117,
		"Seating Capacity": 12,
		"Body Type": "Van",
		"Transmission Type": "Automatic"
	},
	{
		"Car Name": "Chevrolet Express Van 2007",
		"Image": "06856.jpg",
		"Fuel Type": "Gas",
		"Fuel Tank Capacity": 117,
		"Seating Capacity": 12,
		"Body Type": "Van",
		"Transmission Type": "Automatic"
	},
	{
		"Car Name": "Chevrolet HHR SS 2010",
		"Image": "05218.jpg",
		"Fuel Type": "Gas",
		"Fuel Tank Capacity": 60,
		"Seating Capacity": 5,
		"Body Type": "SS",
		"Transmission Type": "Manual"
	},
	{
		"Car Name": "Chevrolet Impala Sedan 2007",
		"Image": "00103.jpg",
		"Fuel Type": "Gas",
		"Fuel Tank Capacity": 64,
		"Seating Capacity": 5,
		"Body Type": "Sedan",
		"Transmission Type": "Automatic"
	},
	{
		"Car Name": "Chevrolet Malibu Hybrid Sedan 2010",
		"Image": "07713.jpg",
		"Fuel Type": "Gas",
		"Fuel Tank Capacity": 60,
		"Seating Capacity": 5,
		"Body Type": "Sedan",
		"Transmission Type": "Automatic"
	},
	{
		"Car Name": "Chevrolet Malibu Sedan 2007",
		"Image": "04221.jpg",
		"Fuel Type": "Gas",
		"Fuel Tank Capacity": 60,
		"Seating Capacity": 5,
		"Body Type": "Sedan",
		"Transmission Type": "Automatic"
	},
	{
		"Car Name": "Chevrolet Monte Carlo Coupe 2007",
		"Image": "02927.jpg",
		"Fuel Type": "Gas",
		"Fuel Tank Capacity": 64,
		"Seating Capacity": 5,
		"Body Type": "Coupe",
		"Transmission Type": "Automatic"
	},
	{
		"Car Name": "Chevrolet Sail U-VA",
		"Image": "chevrolet_sail_u-va.jpg",
		"Fuel Type": "Petrol",
		"Fuel Tank Capacity": 42,
		"Seating Capacity": 5,
		"Body Type": "Hatchback",
		"Transmission Type": "Manual"
	},
	{
		"Car Name": "Chevrolet Silverado 1500 Classic Extended Cab 2007",
		"Image": "02034.jpg",
		"Fuel Type": "Gas",
		"Fuel Tank Capacity": 98,
		"Seating Capacity": 6,
		"Body Type": "Crew Cab",
		"Transmission Type": "Automatic"
	},
	{
		"Car Name": "Chevrolet Silverado 1500 Extended Cab 2012",
		"Image": "07328.jpg",
		"Fuel Type": "Gas",
		"Fuel Tank Capacity": 117,
		"Seating Capacity": 6,
		"Body Type": "Crew Cab",
		"Transmission Type": "Automatic"
	},
	{
		"Car Name": "Chevrolet Silverado 1500 Hybrid Crew Cab 2012",
		"Image": "00174.jpg",
		"Fuel Type": "Gas",
		"Fuel Tank Capacity": 98,
		"Seating Capacity": 6,
		"Body Type": "Crew Cab",
		"Transmission Type": "Automatic"
	},
	{
		"Car Name": "Chevrolet Silverado 1500 Regular Cab 2012",
		"Image": "02934.jpg",
		"Fuel Type": "Gas",
		"Fuel Tank Capacity": 98,
		"Seating Capacity": 6,
		"Body Type": "Crew Cab",
		"Transmission Type": "Automatic"
	},
	{
		"Car Name": "Chevrolet Silverado 2500HD Regular Cab 2012",
		"Image": "05222.jpg",
		"Fuel Type": "Gas",
		"Fuel Tank Capacity": 136,
		"Seating Capacity": 6,
		"Body Type": "Crew Cab",
		"Transmission Type": "Automatic"
	},
	{
		"Car Name": "Chevrolet Sonic Sedan 2012",
		"Image": "04321.jpg",
		"Fuel Type": "Gas",
		"Fuel Tank Capacity": 47,
		"Seating Capacity": 5,
		"Body Type": "Sedan",
		"Transmission Type": "Automatic"
	},
	{
		"Car Name": "Chevrolet Spark",
		"Image": "chevrolet_spark.jpg",
		"Fuel Type": "Petrol",
		"Fuel Tank Capacity": 38,
		"Seating Capacity": 5,
		"Body Type": "Hatchback",
		"Transmission Type": "Manual"
	},
	{
		"Car Name": "Chevrolet Tahoe Hybrid SUV 2012",
		"Image": "02883.jpg",
		"Fuel Type": "Gas",
		"Fuel Tank Capacity": 94,
		"Seating Capacity": 8,
		"Body Type": "SUV",
		"Transmission Type": "Automatic"
	},
	{
		"Car Name": "Chevrolet Tavera Neo 3",
		"Image": "chevrolet_tavera_neo_3.jpg",
		"Fuel Type": "Diesel",
		"Fuel Tank Capacity": 55,
		"Seating Capacity": 10,
		"Body Type": "MUV",
		"Transmission Type": "Manual"
	},
	{
		"Car Name": "Chevrolet TrailBlazer SS 2009",
		"Image": "04249.jpg",
		"Fuel Type": "Gas",
		"Fuel Tank Capacity": 83,
		"Seating Capacity": 5,
		"Body Type": "SS",
		"Transmission Type": "Automatic"
	},
	{
		"Car Name": "Chevrolet Traverse SUV 2012",
		"Image": "00307.jpg",
		"Fuel Type": "Gas",
		"Fuel Tank Capacity": 83,
		"Seating Capacity": 8,
		"Body Type": "SUV",
		"Transmission Type": "Automatic"
	},
	{
		"Car Name": "Chrysler 300 SRT-8 2010",
		"Image": "05628.jpg",
		"Fuel Type": "Gas",
		"Fuel Tank Capacity": 71,
		"Seating Capacity": 5,
		"Body Type": "Sedan",
		"Transmission Type": "Automatic"
	},
	{
		"Car Name": "Chrysler Aspen SUV 2009",
		"Image": "06157.jpg",
		"Fuel Type": "Gas",
		"Fuel Tank Capacity": 102,
		"Seating Capacity": 8,
		"Body Type": "SUV",
		"Transmission Type": "Automatic"
	},
	{
		"Car Name": "Chrysler Crossfire Convertible 2008",
		"Image": "04204.jpg",
		"Fuel Type": "Gas",
		"Fuel Tank Capacity": 60,
		"Seating Capacity": 2,
		"Body Type": "Convertible",
		"Transmission Type": "Manual"
	},
	{
		"Car Name": "Chrysler PT Cruiser Convertible 2008",
		"Image": "06657.jpg",
		"Fuel Type": "Gas",
		"Fuel Tank Capacity": 56,
		"Seating Capacity": 4,
		"Body Type": "Convertible",
		"Transmission Type": "Manual"
	},
	{
		"Car Name": "Chrysler Sebring Convertible 2010",
		"Image": "06147.jpg",
		"Fuel Type": "Gas",
		"Fuel Tank Capacity": 64,
		"Seating Capacity": 4,
		"Body Type": "Convertible",
		"Transmission Type": "Automatic"
	},
	{
		"Car Name": "Chrysler Town and Country Minivan 2012",
		"Image": "00877.jpg",
		"Fuel Type": "Gas",
		"Fuel Tank Capacity": 76,
		"Seating Capacity": 7,
		"Body Type": "Minivan",
		"Transmission Type": "Automatic"
	},
	{
		"Car Name": "Daewoo Nubira Wagon 2002",
		"Image": "02639.jpg",
		"Fuel Type": "Gas",
		"Fuel Tank Capacity": 52,
		"Seating Capacity": 5,
		"Body Type": "Wagon",
		"Transmission Type": "Manual"
	},
	{
		"Car Name": "Datsun Redi-Go",
		"Image": "datsun_redi-go.jpg",
		"Fuel Type": "Petrol",
		"Fuel Tank Capacity": 28,
		"Seating Capacity": 5,
		"Body Type": "Hatchback",
		"Transmission Type": "Automatic"
	},
	{
		"Car Name": "Dodge Caliber Wagon 2007",
		"Image": "04069.jpg",
		"Fuel Type": "Gas",
		"Fuel Tank Capacity": 51,
		"Seating Capacity": 5,
		"Body Type": "Wagon",
		"Transmission Type": "Manual"
	},
	{
		"Car Name": "Dodge Caliber Wagon 2012",
		"Image": "03460.jpg",
		"Fuel Type": "Gas",
		"Fuel Tank Capacity": 102,
		"Seating Capacity": 5,
		"Body Type": "Wagon",
		"Transmission Type": "Manual"
	},
	{
		"Car Name": "Dodge Caravan Minivan 1997",
		"Image": "05888.jpg",
		"Fuel Type": "Gas",
		"Fuel Tank Capacity": 76,
		"Seating Capacity": 5,
		"Body Type": "Minivan",
		"Transmission Type": "Automatic"
	},
	{
		"Car Name": "Dodge Challenger SRT8 2011",
		"Image": "00469.jpg",
		"Fuel Type": "Gas",
		"Fuel Tank Capacity": 74,
		"Seating Capacity": 5,
		"Body Type": "SRT8",
		"Transmission Type": "Automatic"
	},
	{
		"Car Name": "Dodge Charger SRT-8 2009",
		"Image": "03522.jpg",
		"Fuel Type": "Gas",
		"Fuel Tank Capacity": 72,
		"Seating Capacity": 5,
		"Body Type": "SRT8",
		"Transmission Type": "Automatic"
	},
	{
		"Car Name": "Dodge Charger Sedan 2012",
		"Image": "00008.jpg",
		"Fuel Type": "Gas",
		"Fuel Tank Capacity": 72,
		"Seating Capacity": 5,
		"Body Type": "Sedan",
		"Transmission Type": "Automatic"
	},
	{
		"Car Name": "Dodge Dakota Club Cab 2007",
		"Image": "00003.jpg",
		"Fuel Type": "Gas",
		"Fuel Tank Capacity": 83,
		"Seating Capacity": 5,
		"Body Type": "Club Cab",
		"Transmission Type": "Manual"
	},
	{
		"Car Name": "Dodge Dakota Crew Cab 2010",
		"Image": "01212.jpg",
		"Fuel Type": "Gas",
		"Fuel Tank Capacity": 83,
		"Seating Capacity": 4,
		"Body Type": "Crew Cab",
		"Transmission Type": "Automatic"
	},
	{
		"Car Name": "Dodge Durango SUV 2007",
		"Image": "03110.jpg",
		"Fuel Type": "Gas",
		"Fuel Tank Capacity": 102,
		"Seating Capacity": 7,
		"Body Type": "SUV",
		"Transmission Type": "Automatic"
	},
	{
		"Car Name": "Dodge Durango SUV 2012",
		"Image": "05847.jpg",
		"Fuel Type": "Gas",
		"Fuel Tank Capacity": 93,
		"Seating Capacity": 7,
		"Body Type": "SUV",
		"Transmission Type": "Automatic"
	},
	{
		"Car Name": "Dodge Journey SUV 2012",
		"Image": "00349.jpg",
		"Fuel Type": "Gas",
		"Fuel Tank Capacity": 78,
		"Seating Capacity": 5,
		"Body Type": "SUV",
		"Transmission Type": "Automatic"
	},
	{
		"Car Name": "Dodge Magnum Wagon 2008",
		"Image": "05142.jpg",
		"Fuel Type": "Gas",
		"Fuel Tank Capacity": 68,
		"Seating Capacity": 5,
		"Body Type": "Wagon",
		"Transmission Type": "Automatic"
	},
	{
		"Car Name": "Dodge Ram Pickup 3500 Crew Cab 2010",
		"Image": "02494.jpg",
		"Fuel Type": "Diesel",
		"Fuel Tank Capacity": 132,
		"Seating Capacity": 6,
		"Body Type": "Crew Cab",
		"Transmission Type": "Manual"
	},
	{
		"Car Name": "Dodge Ram Pickup 3500 Quad Cab 2009",
		"Image": "06261.jpg",
		"Fuel Type": "Diesel",
		"Fuel Tank Capacity": 132,
		"Seating Capacity": 6,
		"Body Type": "Quad Cab",
		"Transmission Type": "Manual"
	},
	{
		"Car Name": "Dodge Sprinter Cargo Van 2009",
		"Image": "01311.jpg",
		"Fuel Type": "Gas",
		"Fuel Tank Capacity": 95,
		"Seating Capacity": 2,
		"Body Type": "Van",
		"Transmission Type": "Automatic"
	},
	{
		"Car Name": "Eagle Talon Hatchback 1998",
		"Image": "00616.jpg",
		"Fuel Type": "Gas",
		"Fuel Tank Capacity": 64,
		"Seating Capacity": 4,
		"Body Type": "Hatchback",
		"Transmission Type": "Manual"
	},
	{
		"Car Name": "FIAT 500 Abarth 2012",
		"Image": "05709.jpg",
		"Fuel Type": "Gas",
		"Fuel Tank Capacity": 40,
		"Seating Capacity": 4,
		"Body Type": "Hatchback",
		"Transmission Type": "Manual"
	},
	{
		"Car Name": "FIAT 500 Convertible 2012",
		"Image": "05239.jpg",
		"Fuel Type": "Gas",
		"Fuel Tank Capacity": 40,
		"Seating Capacity": 4,
		"Body Type": "Convertible",
		"Transmission Type": "Manual"
	},
	{
		"Car Name": "Ferrari 458 Italia Convertible 2012",
		"Image": "00801.jpg",
		"Fuel Type": "Gas",
		"Fuel Tank Capacity": 86,
		"Seating Capacity": 2,
		"Body Type": "Convertible",
		"Transmission Type": "Automatic"
	},
	{
		"Car Name": "Ferrari 458 Italia Coupe 2012",
		"Image": "07163.jpg",
		"Fuel Type": "Petrol/Gas",
		"Fuel Tank Capacity": 86,
		"Seating Capacity": 2,
		"Body Type": "Coupe",
		"Transmission Type": "Automatic"
	},
	{
		"Car Name": "Ferrari California Convertible 2012",
		"Image": "03978.jpg",
		"Fuel Type": "Petrol/Gas",
		"Fuel Tank Capacity": 70,
		"Seating Capacity": 2,
		"Body Type": "Convertible",
		"Transmission Type": "Automatic"
	},
	{
		"Car Name": "Ferrari FF Coupe 2012",
		"Image": "06031.jpg",
		"Fuel Type": "Petrol/Gas",
		"Fuel Tank Capacity": 78,
		"Seating Capacity": 4,
		"Body Type": "Coupe",
		"Transmission Type": "Automatic"
	},
	{
		"Car Name": "Fiat Grande Punto",
		"Image": "fiat_grande_punto.jpg",
		"Fuel Type": "Petrol",
		"Fuel Tank Capacity": 45,
		"Seating Capacity": 5,
		"Body Type": "Hatchback",
		"Transmission Type": "Manual"
	},
	{
		"Car Name": "Fiat Linea",
		"Image": "fiat_linea.jpg",
		"Fuel Type": "Petrol",
		"Fuel Tank Capacity": 45,
		"Seating Capacity": 5,
		"Body Type": "Sedan",
		"Transmission Type": "Manual"
	},
	{
		"Car Name": "Fiat Punto Evo",
		"Image": "fiat_punto_evo.jpg",
		"Fuel Type": "Petrol",
		"Fuel Tank Capacity": 45,
		"Seating Capacity": 5,
		"Body Type": "Hatchback",
		"Transmission Type": "Manual"
	},
	{
		"Car Name": "Fisker Karma Sedan 2012",
		"Image": "00283.jpg",
		"Fuel Type": "Electric",
		"Fuel Tank Capacity": 36,
		"Seating Capacity": 4,
		"Body Type": "Sedan",
		"Transmission Type": "Automatic"
	},
	{
		"Car Name": "Force One",
		"Image": "force_one.jpg",
		"Fuel Type": "Diesel",
		"Fuel Tank Capacity": 70,
		"Seating Capacity": 7,
		"Body Type": "SUV",
		"Transmission Type": "Manual"
	},
	{
		"Car Name": "Ford E-Series Wagon Van 2012",
		"Image": "05862.jpg",
		"Fuel Type": "Flex-fuel",
		"Fuel Tank Capacity": 132,
		"Seating Capacity": 15,
		"Body Type": "van",
		"Transmission Type": "Automatic"
	},
	{
		"Car Name": "Ford EcoSport",
		"Image": "ford_ecosport.jpg",
		"Fuel Type": "Diesel/Petrol",
		"Fuel Tank Capacity": 52,
		"Seating Capacity": 5,
		"Body Type": "SUV",
		"Transmission Type": "Manual"
	},
	{
		"Car Name": "Ford Edge SUV 2012",
		"Image": "01448.jpg",
		"Fuel Type": "Gas",
		"Fuel Tank Capacity": 72,
		"Seating Capacity": 5,
		"Body Type": "SUV",
		"Transmission Type": "Automatic"
	},
	{
		"Car Name": "Ford Endeavour",
		"Image": "ford_endeavour.jpg",
		"Fuel Type": "Diesel",
		"Fuel Tank Capacity": 80,
		"Seating Capacity": 7,
		"Body Type": "SUV",
		"Transmission Type": "Automatic"
	},
	{
		"Car Name": "Ford Expedition EL SUV 2009",
		"Image": "04034.jpg",
		"Fuel Type": "Flex-fuel",
		"Fuel Tank Capacity": 127,
		"Seating Capacity": 8,
		"Body Type": "SUV",
		"Transmission Type": "Automatic"
	},
	{
		"Car Name": "Ford F-150 Regular Cab 2007",
		"Image": "02588.jpg",
		"Fuel Type": "Gas",
		"Fuel Tank Capacity": 102,
		"Seating Capacity": 3,
		"Body Type": "Cab",
		"Transmission Type": "Manual"
	},
	{
		"Car Name": "Ford F-150 Regular Cab 2012",
		"Image": "04164.jpg",
		"Fuel Type": "Gas",
		"Fuel Tank Capacity": 136,
		"Seating Capacity": 5,
		"Body Type": "Cab",
		"Transmission Type": "Automatic"
	},
	{
		"Car Name": "Ford F-450 Super Duty Crew Cab 2012",
		"Image": "06228.jpg",
		"Fuel Type": "Diesel",
		"Fuel Tank Capacity": 142,
		"Seating Capacity": 5,
		"Body Type": "Crew Cab",
		"Transmission Type": "Automatic"
	},
	{
		"Car Name": "Ford Fiesta Sedan 2012",
		"Image": "06382.jpg",
		"Fuel Type": "Petrol",
		"Fuel Tank Capacity": 43,
		"Seating Capacity": 5,
		"Body Type": "Sedan",
		"Transmission Type": "Manual"
	},
	{
		"Car Name": "Ford Figo 2015",
		"Image": "ford_figo_2015.jpg",
		"Fuel Type": "Petrol/Diesel",
		"Fuel Tank Capacity": 45,
		"Seating Capacity": 5,
		"Body Type": "Hatchback",
		"Transmission Type": "Manual"
	},
	{
		"Car Name": "Ford Figo Aspire",
		"Image": "ford_figo_aspire.jpg",
		"Fuel Type": "Diesel",
		"Fuel Tank Capacity": 40,
		"Seating Capacity": 5,
		"Body Type": "Sedan",
		"Transmission Type": "Manual"
	},
	{
		"Car Name": "Ford Focus Sedan 2007",
		"Image": "01724.jpg",
		"Fuel Type": "Gas",
		"Fuel Tank Capacity": 53,
		"Seating Capacity": 5,
		"Body Type": "Sedan",
		"Transmission Type": "Manual"
	},
	{
		"Car Name": "Ford Freestar Minivan 2007",
		"Image": "04000.jpg",
		"Fuel Type": "Gas",
		"Fuel Tank Capacity": 98,
		"Seating Capacity": 7,
		"Body Type": "Minivan",
		"Transmission Type": "Automatic"
	},
	{
		"Car Name": "Ford GT Coupe 2006",
		"Image": "02573.jpg",
		"Fuel Type": "Gas",
		"Fuel Tank Capacity": 66,
		"Seating Capacity": 2,
		"Body Type": "Coupe",
		"Transmission Type": "Manual"
	},
	{
		"Car Name": "Ford Mustang Convertible 2007",
		"Image": "04236.jpg",
		"Fuel Type": "Gas",
		"Fuel Tank Capacity": 61,
		"Seating Capacity": 4,
		"Body Type": "Convertible",
		"Transmission Type": "Manual"
	},
	{
		"Car Name": "Ford Ranger SuperCab 2011",
		"Image": "00235.jpg",
		"Fuel Type": "Gas",
		"Fuel Tank Capacity": 64,
		"Seating Capacity": 3,
		"Body Type": "Cab",
		"Transmission Type": "Manual"
	},
	{
		"Car Name": "GMC Acadia SUV 2012",
		"Image": "04518.jpg",
		"Fuel Type": "Gas",
		"Fuel Tank Capacity": 83,
		"Seating Capacity": 7,
		"Body Type": "SUV",
		"Transmission Type": "Automatic"
	},
	{
		"Car Name": "GMC Canyon Extended Cab 2012",
		"Image": "03166.jpg",
		"Fuel Type": "Gas",
		"Fuel Tank Capacity": 72,
		"Seating Capacity": 5,
		"Body Type": "Cab",
		"Transmission Type": "Automatic"
	},
	{
		"Car Name": "GMC Savana Van 2012",
		"Image": "02290.jpg",
		"Fuel Type": "Flex-fuel",
		"Fuel Tank Capacity": 117,
		"Seating Capacity": 12,
		"Body Type": "van",
		"Transmission Type": "Automatic"
	},
	{
		"Car Name": "GMC Terrain SUV 2012",
		"Image": "05801.jpg",
		"Fuel Type": "Gas",
		"Fuel Tank Capacity": 98,
		"Seating Capacity": 5,
		"Body Type": "SUV",
		"Transmission Type": "Automatic"
	},
	{
		"Car Name": "GMC Yukon Hybrid SUV 2012",
		"Image": "02179.jpg",
		"Fuel Type": "Gas",
		"Fuel Tank Capacity": 95,
		"Seating Capacity": 8,
		"Body Type": "SUV",
		"Transmission Type": "Automatic"
	},
	{
		"Car Name": "Geo Metro Convertible 1993",
		"Image": "05976.jpg",
		"Fuel Type": "Gas",
		"Fuel Tank Capacity": 40,
		"Seating Capacity": 2,
		"Body Type": "Convertible",
		"Transmission Type": "Manual"
	},
	{
		"Car Name": "HUMMER H2 SUT Crew Cab 2009",
		"Image": "06246.jpg",
		"Fuel Type": "Flex-fuel",
		"Fuel Tank Capacity": 121,
		"Seating Capacity": 5,
		"Body Type": "Crew Cab",
		"Transmission Type": "Automatic"
	},
	{
		"Car Name": "HUMMER H3T Crew Cab 2010",
		"Image": "04800.jpg",
		"Fuel Type": "Gas",
		"Fuel Tank Capacity": 102,
		"Seating Capacity": 5,
		"Body Type": "Crew Cab",
		"Transmission Type": "Automatic"
	},
	{
		"Car Name": "Honda Accord",
		"Image": "honda_accord.jpg",
		"Fuel Type": "Petrol",
		"Fuel Tank Capacity": 60,
		"Seating Capacity": 5,
		"Body Type": "Hybrid",
		"Transmission Type": "Automatic"
	},
	{
		"Car Name": "Honda Accord Coupe 2012",
		"Image": "01422.jpg",
		"Fuel Type": "Gas",
		"Fuel Tank Capacity": 70,
		"Seating Capacity": 5,
		"Body Type": "Coupe",
		"Transmission Type": "Manual"
	},
	{
		"Car Name": "Honda Accord Sedan 2012",
		"Image": "02944.jpg",
		"Fuel Type": "Gas",
		"Fuel Tank Capacity": 70,
		"Seating Capacity": 5,
		"Body Type": "Sedan",
		"Transmission Type": "Automatic"
	},
	{
		"Car Name": "Honda Amaze",
		"Image": "honda_amaze.jpg",
		"Fuel Type": "Diesel",
		"Fuel Tank Capacity": 35,
		"Seating Capacity": 5,
		"Body Type": "Sedan",
		"Transmission Type": "Automatic"
	},
	{
		"Car Name": "Honda Brio",
		"Image": "honda_brio.jpg",
		"Fuel Type": "Petrol",
		"Fuel Tank Capacity": 35,
		"Seating Capacity": 5,
		"Body Type": "Hatchback",
		"Transmission Type": "Manual/Automatic"
	},
	{
		"Car Name": "Honda City",
		"Image": "honda_city.jpg",
		"Fuel Type": "Diesel",
		"Fuel Tank Capacity": 40,
		"Seating Capacity": 5,
		"Body Type": "Sedan",
		"Transmission Type": "Manual"
	},
	{
		"Car Name": "Honda Jazz",
		"Image": "honda_jazz.jpg",
		"Fuel Type": "Petrol",
		"Fuel Tank Capacity": 40,
		"Seating Capacity": 5,
		"Body Type": "Hatchback",
		"Transmission Type": "Automatic"
	},
	{
		"Car Name": "Honda Odyssey Minivan 2007",
		"Image": "01514.jpg",
		"Fuel Type": "Gas",
		"Fuel Tank Capacity": 79,
		"Seating Capacity": "7 to 8",
		"Body Type": "Minivan",
		"Transmission Type": "Automatic"
	},
	{
		"Car Name": "Honda Odyssey Minivan 2012",
		"Image": "05895.jpg",
		"Fuel Type": "Gas",
		"Fuel Tank Capacity": 79,
		"Seating Capacity": "7 to 8",
		"Body Type": "Minivan",
		"Transmission Type": "Automatic"
	},
	{
		"Car Name": "Hyundai Accent Sedan 2012",
		"Image": "06818.jpg",
		"Fuel Type": "Gas",
		"Fuel Tank Capacity": 43,
		"Seating Capacity": 5,
		"Body Type": "Sedan",
		"Transmission Type": "Automatic"
	},
	{
		"Car Name": "Hyundai Azera Sedan 2012",
		"Image": "07348.jpg",
		"Fuel Type": "Gas",
		"Fuel Tank Capacity": 70,
		"Seating Capacity": 5,
		"Body Type": "Sedan",
		"Transmission Type": "Automatic"
	},
	{
		"Car Name": "Hyundai Creta",
		"Image": "hyundai_creta.jpg",
		"Fuel Type": "Diesel",
		"Fuel Tank Capacity": 50,
		"Seating Capacity": 5,
		"Body Type": "SUV",
		"Transmission Type": "Automatic"
	},
	{
		"Car Name": "Hyundai Elantra",
		"Image": "hyundai_elantra.jpg",
		"Fuel Type": "Diesel",
		"Fuel Tank Capacity": 50,
		"Seating Capacity": 5,
		"Body Type": "Sedan",
		"Transmission Type": "Automatic"
	},
	{
		"Car Name": "Hyundai Elantra Sedan 2007",
		"Image": "00133.jpg",
		"Fuel Type": "Gas",
		"Fuel Tank Capacity": 53,
		"Seating Capacity": 5,
		"Body Type": "Sedan",
		"Transmission Type": "Manual"
	},
	{
		"Car Name": "Hyundai Elantra Touring Hatchback 2012",
		"Image": "05134.jpg",
		"Fuel Type": "Gas",
		"Fuel Tank Capacity": 53,
		"Seating Capacity": 5,
		"Body Type": "Hatchback",
		"Transmission Type": "Manual"
	},
	{
		"Car Name": "Hyundai Elite i20",
		"Image": "hyundai_elite_i20.jpg",
		"Fuel Type": "Petrol",
		"Fuel Tank Capacity": 37,
		"Seating Capacity": 5,
		"Body Type": "Hatchback",
		"Transmission Type": "Automatic"
	},
	{
		"Car Name": "Hyundai Eon",
		"Image": "hyundai_eon.jpg",
		"Fuel Type": "Petrol/LPG",
		"Fuel Tank Capacity": 32,
		"Seating Capacity": 5,
		"Body Type": "Hatchback",
		"Transmission Type": "Manual"
	},
	{
		"Car Name": "Hyundai Fluidic Verna",
		"Image": "hyundai_fluidic_verna.jpg",
		"Fuel Type": "Diesel/Petrol",
		"Fuel Tank Capacity": 45,
		"Seating Capacity": 5,
		"Body Type": "Sedan",
		"Transmission Type": "Automatic"
	},
	{
		"Car Name": "Hyundai Genesis Sedan 2012",
		"Image": "00112.jpg",
		"Fuel Type": "Gas",
		"Fuel Tank Capacity": 73,
		"Seating Capacity": 5,
		"Body Type": "Sedan",
		"Transmission Type": "Automatic"
	},
	{
		"Car Name": "Hyundai Grand i10",
		"Image": "hyundai_grand_i10.jpg",
		"Fuel Type": "Petrol",
		"Fuel Tank Capacity": 43,
		"Seating Capacity": 5,
		"Body Type": "Hatchback",
		"Transmission Type": "Manual"
	},
	{
		"Car Name": "Hyundai Santa Fe",
		"Image": "hyundai_santa_fe.jpg",
		"Fuel Type": "Diesel",
		"Fuel Tank Capacity": 64,
		"Seating Capacity": 7,
		"Body Type": "SUV",
		"Transmission Type": "Manual/Automatic"
	},
	{
		"Car Name": "Hyundai Santa Fe SUV 2012",
		"Image": "01279.jpg",
		"Fuel Type": "Diesel",
		"Fuel Tank Capacity": 64,
		"Seating Capacity": 7,
		"Body Type": "SUV",
		"Transmission Type": "Manual"
	},
	{
		"Car Name": "Hyundai Santro Xing",
		"Image": "hyundai_santro_xing.jpg",
		"Fuel Type": "Petrol",
		"Fuel Tank Capacity": 35,
		"Seating Capacity": 5,
		"Body Type": "Hatchback",
		"Transmission Type": "Manual"
	},
	{
		"Car Name": "Hyundai Sonata Hybrid Sedan 2012",
		"Image": "02560.jpg",
		"Fuel Type": "Gas",
		"Fuel Tank Capacity": 65,
		"Seating Capacity": 5,
		"Body Type": "Sedan",
		"Transmission Type": "Automatic"
	},
	{
		"Car Name": "Hyundai Sonata Sedan 2012",
		"Image": "04682.jpg",
		"Fuel Type": "Gas",
		"Fuel Tank Capacity": 70,
		"Seating Capacity": 5,
		"Body Type": "Sedan",
		"Transmission Type": "Automatic"
	},
	{
		"Car Name": "Hyundai Tucson SUV 2012",
		"Image": "04895.jpg",
		"Fuel Type": "Gas",
		"Fuel Tank Capacity": 58,
		"Seating Capacity": 5,
		"Body Type": "SUV",
		"Transmission Type": "Automatic"
	},
	{
		"Car Name": "Hyundai Veloster Hatchback 2012",
		"Image": "04165.jpg",
		"Fuel Type": "Gas",
		"Fuel Tank Capacity": 50,
		"Seating Capacity": 4,
		"Body Type": "Hatchback",
		"Transmission Type": "Manual"
	},
	{
		"Car Name": "Hyundai Veracruz SUV 2012",
		"Image": "07201.jpg",
		"Fuel Type": "Gas",
		"Fuel Tank Capacity": 78,
		"Seating Capacity": 7,
		"Body Type": "SUV",
		"Transmission Type": "Automatic"
	},
	{
		"Car Name": "Hyundai Verna 2017",
		"Image": "hyundai_verna_2017.jpg",
		"Fuel Type": "Petrol",
		"Fuel Tank Capacity": 45,
		"Seating Capacity": 5,
		"Body Type": "Sedan",
		"Transmission Type": "Manual"
	},
	{
		"Car Name": "Hyundai Xcent",
		"Image": "hyundai_xcent.jpg",
		"Fuel Type": "Petrol",
		"Fuel Tank Capacity": 43,
		"Seating Capacity": 5,
		"Body Type": "Sedan",
		"Transmission Type": "Manual"
	},
	{
		"Car Name": "Hyundai i10",
		"Image": "hyundai_i10.jpg",
		"Fuel Type": "Petrol",
		"Fuel Tank Capacity": 35,
		"Seating Capacity": 5,
		"Body Type": "Hatchback",
		"Transmission Type": "Manual"
	},
	{
		"Car Name": "Hyundai i20",
		"Image": "hyundai_i20.jpg",
		"Fuel Type": "Petrol",
		"Fuel Tank Capacity": 37,
		"Seating Capacity": 5,
		"Body Type": "Hatchback",
		"Transmission Type": "Automatic"
	},
	{
		"Car Name": "Hyundai i20 Active",
		"Image": "hyundai_i20_active.jpg",
		"Fuel Type": "Petrol",
		"Fuel Tank Capacity": 45,
		"Seating Capacity": 5,
		"Body Type": "Hatchback",
		"Transmission Type": "Manual"
	},
	{
		"Car Name": "Infiniti G Coupe IPL 2012",
		"Image": "02894.jpg",
		"Fuel Type": "Gas",
		"Fuel Tank Capacity": 76,
		"Seating Capacity": 4,
		"Body Type": "Coupe",
		"Transmission Type": "Manual"
	},
	{
		"Car Name": "Infiniti QX56 SUV 2011",
		"Image": "00040.jpg",
		"Fuel Type": "Gas",
		"Fuel Tank Capacity": 98,
		"Seating Capacity": 7,
		"Body Type": "SUV",
		"Transmission Type": "Automatic"
	},
	{
		"Car Name": "Isuzu Ascender SUV 2008",
		"Image": "03275.jpg",
		"Fuel Type": "Gas",
		"Fuel Tank Capacity": 82,
		"Seating Capacity": 5,
		"Body Type": "SUV",
		"Transmission Type": "Automatic"
	},
	{
		"Car Name": "Jaguar XF",
		"Image": "jaguar_xf.jpg",
		"Fuel Type": "Petrol",
		"Fuel Tank Capacity": 66,
		"Seating Capacity": 5,
		"Body Type": "Sedan",
		"Transmission Type": "Automatic"
	},
	{
		"Car Name": "Jaguar XK XKR 2012",
		"Image": "02487.jpg",
		"Fuel Type": "Gas",
		"Fuel Tank Capacity": 61,
		"Seating Capacity": 4,
		"Body Type": "Convertible",
		"Transmission Type": "Automatic"
	},
	{
		"Car Name": "Jeep Compass",
		"Image": "jeep_compass.jpg",
		"Fuel Type": "Diesel",
		"Fuel Tank Capacity": 60,
		"Seating Capacity": 5,
		"Body Type": "SUV",
		"Transmission Type": "Automatic"
	},
	{
		"Car Name": "Jeep Compass SUV 2012",
		"Image": "01045.jpg",
		"Fuel Type": "Gas",
		"Fuel Tank Capacity": 51,
		"Seating Capacity": 5,
		"Body Type": "SUV",
		"Transmission Type": "Automatic"
	},
	{
		"Car Name": "Jeep Grand Cherokee SUV 2012",
		"Image": "08065.jpg",
		"Fuel Type": "Flex-fuel",
		"Fuel Tank Capacity": 93,
		"Seating Capacity": 5,
		"Body Type": "SUV",
		"Transmission Type": "Automatic"
	},
	{
		"Car Name": "Jeep Liberty SUV 2012",
		"Image": "00545.jpg",
		"Fuel Type": "Gas",
		"Fuel Tank Capacity": 74,
		"Seating Capacity": 5,
		"Body Type": "SUV",
		"Transmission Type": "Automatic"
	},
	{
		"Car Name": "Jeep Patriot SUV 2012",
		"Image": "00610.jpg",
		"Fuel Type": "Gas",
		"Fuel Tank Capacity": 51,
		"Seating Capacity": 5,
		"Body Type": "SUV",
		"Transmission Type": "Automatic"
	},
	{
		"Car Name": "Jeep Wrangler SUV 2012",
		"Image": "03089.jpg",
		"Fuel Type": "Gas",
		"Fuel Tank Capacity": 70,
		"Seating Capacity": 4,
		"Body Type": "SUV",
		"Transmission Type": "Manual"
	},
	{
		"Car Name": "Lamborghini Aventador Coupe 2012",
		"Image": "05397.jpg",
		"Fuel Type": "Gas",
		"Fuel Tank Capacity": 90,
		"Seating Capacity": 2,
		"Body Type": "Coupe",
		"Transmission Type": "Automatic"
	},
	{
		"Car Name": "Lamborghini Diablo Coupe 2001",
		"Image": "02489.jpg",
		"Fuel Type": "Gas",
		"Fuel Tank Capacity": 100,
		"Seating Capacity": 2,
		"Body Type": "Coupe",
		"Transmission Type": "Manual"
	},
	{
		"Car Name": "Lamborghini Gallardo LP 570-4 Superleggera 2012",
		"Image": "00587.jpg",
		"Fuel Type": "Gas",
		"Fuel Tank Capacity": 90,
		"Seating Capacity": 2,
		"Body Type": "Coupe",
		"Transmission Type": "Automatic"
	},
	{
		"Car Name": "Lamborghini Reventon Coupe 2008",
		"Image": "06526.jpg",
		"Fuel Type": "Gas",
		"Fuel Tank Capacity": 100,
		"Seating Capacity": 2,
		"Body Type": "Coupe",
		"Transmission Type": "Automatic"
	},
	{
		"Car Name": "Land Rover LR2 SUV 2012",
		"Image": "05131.jpg",
		"Fuel Type": "Gas",
		"Fuel Tank Capacity": 70,
		"Seating Capacity": 5,
		"Body Type": "SUV",
		"Transmission Type": "Automatic"
	},
	{
		"Car Name": "Land Rover Range Rover",
		"Image": "land_rover_range_rover.jpg",
		"Fuel Type": "Diesel/Petrol",
		"Fuel Tank Capacity": 105,
		"Seating Capacity": 5,
		"Body Type": "SUV",
		"Transmission Type": "Automatic"
	},
	{
		"Car Name": "Land Rover Range Rover Evoque",
		"Image": "land_rover_range_rover_evoque.jpg",
		"Fuel Type": "Petrol",
		"Fuel Tank Capacity": 66,
		"Seating Capacity": 5,
		"Body Type": "SUV",
		"Transmission Type": "Automatic"
	},
	{
		"Car Name": "Land Rover Range Rover SUV 2012",
		"Image": "00535.jpg",
		"Fuel Type": "Gas",
		"Fuel Tank Capacity": 105,
		"Seating Capacity": 5,
		"Body Type": "SUV",
		"Transmission Type": "Automatic"
	},
	{
		"Car Name": "Lincoln Town Car Sedan 2011",
		"Image": "02210.jpg",
		"Fuel Type": "Flex fuel",
		"Fuel Tank Capacity": 72,
		"Seating Capacity": 6,
		"Body Type": "Sedan",
		"Transmission Type": "Automatic"
	},
	{
		"Car Name": "MINI Cooper Roadster Convertible 2012",
		"Image": "04935.jpg",
		"Fuel Type": "Gas",
		"Fuel Tank Capacity": 50,
		"Seating Capacity": 2,
		"Body Type": "Convertible",
		"Transmission Type": "Automatic / Manual"
	},
	{
		"Car Name": "Mahindra Bolero",
		"Image": "mahindra_bolero.jpg",
		"Fuel Type": "Diesel",
		"Fuel Tank Capacity": 60,
		"Seating Capacity": 7,
		"Body Type": "SUV",
		"Transmission Type": "Manual"
	},
	{
		"Car Name": "Mahindra KUV100",
		"Image": "mahindra_kuv100.jpg",
		"Fuel Type": "Petrol",
		"Fuel Tank Capacity": 35,
		"Seating Capacity": 6,
		"Body Type": "Hatchback",
		"Transmission Type": "Manual"
	},
	{
		"Car Name": "Mahindra Quanto",
		"Image": "mahindra_quanto.jpg",
		"Fuel Type": "Diesel",
		"Fuel Tank Capacity": 55,
		"Seating Capacity": 7,
		"Body Type": "SUV",
		"Transmission Type": "Manual"
	},
	{
		"Car Name": "Mahindra Scorpio",
		"Image": "mahindra_scorpio.jpg",
		"Fuel Type": "Diesel",
		"Fuel Tank Capacity": 60,
		"Seating Capacity": 7,
		"Body Type": "SUV",
		"Transmission Type": "Manual"
	},
	{
		"Car Name": "Mahindra Thar",
		"Image": "mahindra_thar.jpg",
		"Fuel Type": "Diesel",
		"Fuel Tank Capacity": 57,
		"Seating Capacity": 4,
		"Body Type": "SUV",
		"Transmission Type": "Automatic"
	},
	{
		"Car Name": "Mahindra Verito",
		"Image": "mahindra_verito.jpg",
		"Fuel Type": "Petrol",
		"Fuel Tank Capacity": 50,
		"Seating Capacity": 5,
		"Body Type": "Sedan",
		"Transmission Type": "Manual"
	},
	{
		"Car Name": "Mahindra XUV500",
		"Image": "mahindra_xuv500.jpg",
		"Fuel Type": "Diesel",
		"Fuel Tank Capacity": 70,
		"Seating Capacity": 7,
		"Body Type": "SUV",
		"Transmission Type": "Automatic"
	},
	{
		"Car Name": "Mahindra Xylo",
		"Image": "mahindra_xylo.jpg",
		"Fuel Type": "Diesel",
		"Fuel Tank Capacity": 55,
		"Seating Capacity": 8,
		"Body Type": "MUV",
		"Transmission Type": "Manual"
	},
	{
		"Car Name": "Maruti Suzuki Alto 800",
		"Image": "maruti_suzuki_alto_800.jpg",
		"Fuel Type": "CNG",
		"Fuel Tank Capacity": 60,
		"Seating Capacity": 5,
		"Body Type": "Hatchback",
		"Transmission Type": "Manual"
	},
	{
		"Car Name": "Maruti Suzuki Alto K10",
		"Image": "maruti_suzuki_alto_k10.jpg",
		"Fuel Type": "Petrol",
		"Fuel Tank Capacity": 35,
		"Seating Capacity": 5,
		"Body Type": "Hatchback",
		"Transmission Type": "Manual"
	},
	{
		"Car Name": "Maruti Suzuki Baleno",
		"Image": "maruti_suzuki_baleno.jpg",
		"Fuel Type": "Petrol",
		"Fuel Tank Capacity": 37,
		"Seating Capacity": 5,
		"Body Type": "Hatchback",
		"Transmission Type": "Automatic"
	},
	{
		"Car Name": "Maruti Suzuki Celerio",
		"Image": "maruti_suzuki_celerio.jpg",
		"Fuel Type": "CNG",
		"Fuel Tank Capacity": 60,
		"Seating Capacity": 5,
		"Body Type": "Hatchback",
		"Transmission Type": "Manual"
	},
	{
		"Car Name": "Maruti Suzuki Ciaz",
		"Image": "maruti_suzuki_ciaz.jpg",
		"Fuel Type": "Petrol",
		"Fuel Tank Capacity": 43,
		"Seating Capacity": 5,
		"Body Type": "Sedan",
		"Transmission Type": "Automatic"
	},
	{
		"Car Name": "Maruti Suzuki Eeco",
		"Image": "maruti_suzuki_eeco.jpg",
		"Fuel Type": "CNG",
		"Fuel Tank Capacity": 65,
		"Seating Capacity": 5,
		"Body Type": "Minivan",
		"Transmission Type": "Manual"
	},
	{
		"Car Name": "Maruti Suzuki Grand Vitara",
		"Image": "maruti_suzuki_grand_vitara.jpg",
		"Fuel Type": "Diesel",
		"Fuel Tank Capacity": 66,
		"Seating Capacity": 5,
		"Body Type": "SUV",
		"Transmission Type": "Manual"
	},
	{
		"Car Name": "Maruti Suzuki Gypsy",
		"Image": "maruti_suzuki_gypsy.jpg",
		"Fuel Type": "Petrol",
		"Fuel Tank Capacity": 40,
		"Seating Capacity": 8,
		"Body Type": "SUV",
		"Transmission Type": "Manual"
	},
	{
		"Car Name": "Maruti Suzuki Ignis",
		"Image": "maruti_suzuki_ignis.jpg",
		"Fuel Type": "Petrol",
		"Fuel Tank Capacity": 32,
		"Seating Capacity": 5,
		"Body Type": "Hatchback",
		"Transmission Type": "Automatic"
	},
	{
		"Car Name": "Maruti Suzuki Omni",
		"Image": "maruti_suzuki_omni.jpg",
		"Fuel Type": "Petrol",
		"Fuel Tank Capacity": 36,
		"Seating Capacity": 5,
		"Body Type": "Minivan",
		"Transmission Type": "Manual"
	},
	{
		"Car Name": "Maruti Suzuki S-Cross",
		"Image": "maruti_suzuki_s-cross.jpg",
		"Fuel Type": "Petrol",
		"Fuel Tank Capacity": 48,
		"Seating Capacity": 5,
		"Body Type": "SUV",
		"Transmission Type": "Automatic"
	},
	{
		"Car Name": "Maruti Suzuki SX4",
		"Image": "maruti_suzuki_sx4.jpg",
		"Fuel Type": "Petrol",
		"Fuel Tank Capacity": 50,
		"Seating Capacity": 5,
		"Body Type": "Sedan",
		"Transmission Type": "Manual"
	},
	{
		"Car Name": "Maruti Suzuki Stingray",
		"Image": "maruti_suzuki_stingray.jpg",
		"Fuel Type": "Petrol",
		"Fuel Tank Capacity": 35,
		"Seating Capacity": 5,
		"Body Type": "Hatchback",
		"Transmission Type": "Manual"
	},
	{
		"Car Name": "Maruti Suzuki Swift",
		"Image": "maruti_suzuki_swift.jpg",
		"Fuel Type": "Petrol",
		"Fuel Tank Capacity": 37,
		"Seating Capacity": 5,
		"Body Type": "Hatchback",
		"Transmission Type": "Automatic"
	},
	{
		"Car Name": "Maruti Suzuki Swift Dzire",
		"Image": "maruti_suzuki_swift_dzire.jpg",
		"Fuel Type": "Petrol",
		"Fuel Tank Capacity": 37,
		"Seating Capacity": 5,
		"Body Type": "Sedan",
		"Transmission Type": "Automatic"
	},
	{
		"Car Name": "Maruti Suzuki Vitara Brezza",
		"Image": "maruti_suzuki_vitara_brezza.jpg",
		"Fuel Type": "Petrol",
		"Fuel Tank Capacity": 48,
		"Seating Capacity": 5,
		"Body Type": "SUV",
		"Transmission Type": "Automatic"
	},
	{
		"Car Name": "Maruti Suzuki Wagon R",
		"Image": "maruti_suzuki_wagon_r.jpg",
		"Fuel Type": "Petrol",
		"Fuel Tank Capacity": 32,
		"Seating Capacity": 5,
		"Body Type": "Hatchback",
		"Transmission Type": "Automatic"
	},
	{
		"Car Name": "Maybach Landaulet Convertible 2012",
		"Image": "01973.jpg",
		"Fuel Type": "Gas",
		"Fuel Tank Capacity": 110,
		"Seating Capacity": "4 to 5",
		"Body Type": "Convertible",
		"Transmission Type": "Automatic"
	},
	{
		"Car Name": "Mazda Tribute SUV 2011",
		"Image": "07255.jpg",
		"Fuel Type": "Flex fuel",
		"Fuel Tank Capacity": 66,
		"Seating Capacity": 5,
		"Body Type": "SUV",
		"Transmission Type": "Automatic"
	},
	{
		"Car Name": "McLaren MP4-12C Coupe 2012",
		"Image": "00187.jpg",
		"Fuel Type": "Gas",
		"Fuel Tank Capacity": 72,
		"Seating Capacity": 2,
		"Body Type": "Coupe",
		"Transmission Type": "Automatic"
	},
	{
		"Car Name": "Mercedes-Benz 300-Class Convertible 1993",
		"Image": "00120.jpg",
		"Fuel Type": "Gas",
		"Fuel Tank Capacity": 80,
		"Seating Capacity": 4,
		"Body Type": "Convertible",
		"Transmission Type": "Manual"
	},
	{
		"Car Name": "Mercedes-Benz C-Class Sedan 2012",
		"Image": "04423.jpg",
		"Fuel Type": "Gas",
		"Fuel Tank Capacity": 66,
		"Seating Capacity": 5,
		"Body Type": "Sedan",
		"Transmission Type": "Automatic"
	},
	{
		"Car Name": "Mercedes-Benz E-Class Sedan 2012",
		"Image": "03979.jpg",
		"Fuel Type": "Gas",
		"Fuel Tank Capacity": 89,
		"Seating Capacity": 5,
		"Body Type": "Sedan",
		"Transmission Type": "Automatic"
	},
	{
		"Car Name": "Mercedes-Benz S-Class Sedan 2012",
		"Image": "00396.jpg",
		"Fuel Type": "Diesel",
		"Fuel Tank Capacity": 90,
		"Seating Capacity": 5,
		"Body Type": "Sedan",
		"Transmission Type": "Automatic"
	},
	{
		"Car Name": "Mercedes-Benz SL-Class Coupe 2009",
		"Image": "01842.jpg",
		"Fuel Type": "Gas",
		"Fuel Tank Capacity": 80,
		"Seating Capacity": 2,
		"Body Type": "Coupe",
		"Transmission Type": "Automatic"
	},
	{
		"Car Name": "Mercedes-Benz Sprinter Van 2012",
		"Image": "00804.jpg",
		"Fuel Type": "Diesel",
		"Fuel Tank Capacity": 95,
		"Seating Capacity": "",
		"Body Type": "Van",
		"Transmission Type": "Automatic"
	},
	{
		"Car Name": "Mitsubishi Lancer Sedan 2012",
		"Image": "04766.jpg",
		"Fuel Type": "Gas",
		"Fuel Tank Capacity": 59,
		"Seating Capacity": 5,
		"Body Type": "Sedan",
		"Transmission Type": "Automatic"
	},
	{
		"Car Name": "Nissan 240SX Coupe 1998",
		"Image": "05300.jpg",
		"Fuel Type": "Gas",
		"Fuel Tank Capacity": 65,
		"Seating Capacity": 4,
		"Body Type": "Coupe",
		"Transmission Type": "Manual"
	},
	{
		"Car Name": "Nissan Juke Hatchback 2012",
		"Image": "01141.jpg",
		"Fuel Type": "Gas",
		"Fuel Tank Capacity": 45,
		"Seating Capacity": 5,
		"Body Type": "Hatchback",
		"Transmission Type": "Manual"
	},
	{
		"Car Name": "Nissan Leaf Hatchback 2012",
		"Image": "01910.jpg",
		"Fuel Type": "Electric",
		"Fuel Tank Capacity": "nill",
		"Seating Capacity": 5,
		"Body Type": "Hatchback",
		"Transmission Type": "Automatic"
	},
	{
		"Car Name": "Nissan Micra",
		"Image": "nissan_micra.jpg",
		"Fuel Type": "Petrol",
		"Fuel Tank Capacity": 41,
		"Seating Capacity": 5,
		"Body Type": "Hatchback",
		"Transmission Type": "Automatic"
	},
	{
		"Car Name": "Nissan Micra Active",
		"Image": "nissan_micra_active.jpg",
		"Fuel Type": "Petrol",
		"Fuel Tank Capacity": 41,
		"Seating Capacity": 5,
		"Body Type": "Hatchback",
		"Transmission Type": "Manual"
	},
	{
		"Car Name": "Nissan NV Passenger Van 2012",
		"Image": "05355.jpg",
		"Fuel Type": "Gas",
		"Fuel Tank Capacity": 106,
		"Seating Capacity": 12,
		"Body Type": "Van",
		"Transmission Type": "Automatic"
	},
	{
		"Car Name": "Nissan Sunny",
		"Image": "nissan_sunny.jpg",
		"Fuel Type": "Petrol",
		"Fuel Tank Capacity": 41,
		"Seating Capacity": 5,
		"Body Type": "Sedan",
		"Transmission Type": "Manual"
	},
	{
		"Car Name": "Nissan Terrano",
		"Image": "nissan_terrano.jpg",
		"Fuel Type": "Diesel",
		"Fuel Tank Capacity": 50,
		"Seating Capacity": 5,
		"Body Type": "SUV",
		"Transmission Type": "Manual"
	},
	{
		"Car Name": "Plymouth Neon Coupe 1999",
		"Image": "01310.jpg",
		"Fuel Type": "Gas",
		"Fuel Tank Capacity": 47,
		"Seating Capacity": 5,
		"Body Type": "Coupe",
		"Transmission Type": "Manual"
	},
	{
		"Car Name": "Porsche Panamera Sedan 2012",
		"Image": "00210.jpg",
		"Fuel Type": "Gas",
		"Fuel Tank Capacity": 80,
		"Seating Capacity": 4,
		"Body Type": "Hatchback",
		"Transmission Type": "Automatic / Manual"
	},
	{
		"Car Name": "Ram C-V Cargo Van Minivan 2012",
		"Image": "07356.jpg",
		"Fuel Type": "Flex fuel",
		"Fuel Tank Capacity": 75,
		"Seating Capacity": 2,
		"Body Type": "Caravan",
		"Transmission Type": "Automatic"
	},
	{
		"Car Name": "Renault Duster",
		"Image": "renault_duster.jpg",
		"Fuel Type": "Petrol",
		"Fuel Tank Capacity": 50,
		"Seating Capacity": 5,
		"Body Type": "SUV",
		"Transmission Type": "Automatic"
	},
	{
		"Car Name": "Renault KWID",
		"Image": "renault_kwid.jpg",
		"Fuel Type": "Petrol",
		"Fuel Tank Capacity": 28,
		"Seating Capacity": 5,
		"Body Type": "Hatchback",
		"Transmission Type": "Automatic"
	},
	{
		"Car Name": "Renault Lodgy",
		"Image": "renault_lodgy.jpg",
		"Fuel Type": "Diesel",
		"Fuel Tank Capacity": 50,
		"Seating Capacity": 8,
		"Body Type": "MUV",
		"Transmission Type": "Manual"
	},
	{
		"Car Name": "Renault Pulse",
		"Image": "renault_pulse.jpg",
		"Fuel Type": "Petrol",
		"Fuel Tank Capacity": 41,
		"Seating Capacity": 5,
		"Body Type": "Hatchback",
		"Transmission Type": "Manual"
	},
	{
		"Car Name": "Rolls-Royce Ghost Sedan 2012",
		"Image": "03201.jpg",
		"Fuel Type": "Gas",
		"Fuel Tank Capacity": 82,
		"Seating Capacity": 5,
		"Body Type": "Sedan",
		"Transmission Type": "Automatic"
	},
	{
		"Car Name": "Rolls-Royce Phantom Drophead Coupe Convertible 2012",
		"Image": "07975.jpg",
		"Fuel Type": "Gas",
		"Fuel Tank Capacity": 80,
		"Seating Capacity": 4,
		"Body Type": "Coupe",
		"Transmission Type": "Automatic"
	},
	{
		"Car Name": "Rolls-Royce Phantom Sedan 2012",
		"Image": "03248.jpg",
		"Fuel Type": "Gas",
		"Fuel Tank Capacity": 100,
		"Seating Capacity": 5,
		"Body Type": "Sedan",
		"Transmission Type": "Automatic"
	},
	{
		"Car Name": "Scion xD Hatchback 2012",
		"Image": "02937.jpg",
		"Fuel Type": "Gas",
		"Fuel Tank Capacity": 42,
		"Seating Capacity": 5,
		"Body Type": "Hatchback",
		"Transmission Type": "Automatic"
	},
	{
		"Car Name": "Skoda Rapid",
		"Image": "skoda_rapid.jpg",
		"Fuel Type": "Petrol",
		"Fuel Tank Capacity": 55,
		"Seating Capacity": 5,
		"Body Type": "Sedan",
		"Transmission Type": "Automatic"
	},
	{
		"Car Name": "Skoda Superb",
		"Image": "skoda_superb.jpg",
		"Fuel Type": "Petrol",
		"Fuel Tank Capacity": 66,
		"Seating Capacity": 5,
		"Body Type": "Sedan",
		"Transmission Type": "Automatic"
	},
	{
		"Car Name": "Skoda Yeti",
		"Image": "skoda_yeti.jpg",
		"Fuel Type": "Diesel",
		"Fuel Tank Capacity": 55,
		"Seating Capacity": 5,
		"Body Type": "SUV",
		"Transmission Type": "Manual"
	},
	{
		"Car Name": "Spyker C8 Convertible 2009",
		"Image": "05180.jpg",
		"Fuel Type": "Gas",
		"Fuel Tank Capacity": 75,
		"Seating Capacity": 2,
		"Body Type": "Convertible",
		"Transmission Type": "Manual"
	},
	{
		"Car Name": "Spyker C8 Coupe 2009",
		"Image": "00029.jpg",
		"Fuel Type": "Gas",
		"Fuel Tank Capacity": 57,
		"Seating Capacity": 2,
		"Body Type": "Coupe",
		"Transmission Type": "Manual"
	},
	{
		"Car Name": "Suzuki Aerio Sedan 2007",
		"Image": "05018.jpg",
		"Fuel Type": "Gas",
		"Fuel Tank Capacity": 50,
		"Seating Capacity": 5,
		"Body Type": "Sedan",
		"Transmission Type": "Manual / Automatic"
	},
	{
		"Car Name": "Suzuki Kizashi Sedan 2012",
		"Image": "00460.jpg",
		"Fuel Type": "Gas",
		"Fuel Tank Capacity": 63,
		"Seating Capacity": 5,
		"Body Type": "Sedan",
		"Transmission Type": "Manual"
	},
	{
		"Car Name": "Suzuki SX4 Hatchback 2012",
		"Image": "00475.jpg",
		"Fuel Type": "Gas",
		"Fuel Tank Capacity": 50,
		"Seating Capacity": 5,
		"Body Type": "Hatchback",
		"Transmission Type": "Manual"
	},
	{
		"Car Name": "Suzuki SX4 Sedan 2012",
		"Image": "05422.jpg",
		"Fuel Type": "Gas",
		"Fuel Tank Capacity": 50,
		"Seating Capacity": 5,
		"Body Type": "Sedan",
		"Transmission Type": "Manual"
	},
	{
		"Car Name": "Tata Aria",
		"Image": "tata_aria.jpg",
		"Fuel Type": "Diesel",
		"Fuel Tank Capacity": 65,
		"Seating Capacity": 7,
		"Body Type": "MUV",
		"Transmission Type": "Automatic"
	},
	{
		"Car Name": "Tata Bolt",
		"Image": "tata_bolt.jpg",
		"Fuel Type": "Petrol",
		"Fuel Tank Capacity": 44,
		"Seating Capacity": 5,
		"Body Type": "Hatchback",
		"Transmission Type": "Manual"
	},
	{
		"Car Name": "Tata Hexa",
		"Image": "tata_hexa.jpg",
		"Fuel Type": "Diesel",
		"Fuel Tank Capacity": 60,
		"Seating Capacity": 7,
		"Body Type": "SUV",
		"Transmission Type": "Manual"
	},
	{
		"Car Name": "Tata Indica Vista",
		"Image": "tata_indica_vista.jpg",
		"Fuel Type": "Diesel",
		"Fuel Tank Capacity": 37,
		"Seating Capacity": 5,
		"Body Type": "Hatchback",
		"Transmission Type": "Manual"
	},
	{
		"Car Name": "Tata Indica eV2",
		"Image": "tata_indica_ev2.jpg",
		"Fuel Type": "Petrol",
		"Fuel Tank Capacity": 37,
		"Seating Capacity": 5,
		"Body Type": "Hatchback",
		"Transmission Type": "Manual"
	},
	{
		"Car Name": "Tata Indigo eCS",
		"Image": "tata_indigo_ecs.jpg",
		"Fuel Type": "Petrol",
		"Fuel Tank Capacity": 42,
		"Seating Capacity": 5,
		"Body Type": "Sedan",
		"Transmission Type": "Manual"
	},
	{
		"Car Name": "Tata Nano",
		"Image": "tata_nano.jpg",
		"Fuel Type": "Diesel",
		"Fuel Tank Capacity": 15,
		"Seating Capacity": 4,
		"Body Type": "Hatchback",
		"Transmission Type": "Manual"
	},
	{
		"Car Name": "Tata Nano GenX",
		"Image": "tata_nano_genx.jpg",
		"Fuel Type": "Petrol",
		"Fuel Tank Capacity": 24,
		"Seating Capacity": 4,
		"Body Type": "Hatchback",
		"Transmission Type": "Manual"
	},
	{
		"Car Name": "Tata Safari",
		"Image": "tata_safari.jpg",
		"Fuel Type": "Diesel",
		"Fuel Tank Capacity": 65,
		"Seating Capacity": 7,
		"Body Type": "SUV",
		"Transmission Type": "Manual"
	},
	{
		"Car Name": "Tata Safari Storme",
		"Image": "tata_safari_storme.jpg",
		"Fuel Type": "Diesel",
		"Fuel Tank Capacity": 63,
		"Seating Capacity": 5,
		"Body Type": "SUV",
		"Transmission Type": "Manual"
	},
	{
		"Car Name": "Tata Sumo Gold",
		"Image": "tata_sumo_gold.jpg",
		"Fuel Type": "Diesel",
		"Fuel Tank Capacity": 65,
		"Seating Capacity": 7,
		"Body Type": "SUV",
		"Transmission Type": "Manual"
	},
	{
		"Car Name": "Tata Tiago",
		"Image": "tata_tiago.jpg",
		"Fuel Type": "Petrol",
		"Fuel Tank Capacity": 35,
		"Seating Capacity": 5,
		"Body Type": "Hatchback",
		"Transmission Type": "Automatic"
	},
	{
		"Car Name": "Tata Tigor",
		"Image": "tata_tigor.jpg",
		"Fuel Type": "Petrol",
		"Fuel Tank Capacity": 35,
		"Seating Capacity": 5,
		"Body Type": "Sedan",
		"Transmission Type": "Automatic"
	},
	{
		"Car Name": "Tata Zest",
		"Image": "tata_zest.jpg",
		"Fuel Type": "Petrol",
		"Fuel Tank Capacity": 44,
		"Seating Capacity": 5,
		"Body Type": "Sedan",
		"Transmission Type": "Manual"
	},
	{
		"Car Name": "Tesla Model S Sedan 2012",
		"Image": "05795.jpg",
		"Fuel Type": "Electric",
		"Fuel Tank Capacity": "nill",
		"Seating Capacity": 5,
		"Body Type": "Sedan",
		"Transmission Type": "Single speed fixed gear"
	},
	{
		"Car Name": "Toyota 4Runner SUV 2012",
		"Image": "03794.jpg",
		"Fuel Type": "Gas",
		"Fuel Tank Capacity": 87,
		"Seating Capacity": 5,
		"Body Type": "SUV",
		"Transmission Type": "Automatic"
	},
	{
		"Car Name": "Toyota Camry",
		"Image": "toyota_camry.jpg",
		"Fuel Type": "Petrol",
		"Fuel Tank Capacity": 50,
		"Seating Capacity": 5,
		"Body Type": "Sedan",
		"Transmission Type": "Automatic"
	},
	{
		"Car Name": "Toyota Camry Sedan 2012",
		"Image": "02423.jpg",
		"Fuel Type": "Gas",
		"Fuel Tank Capacity": 65,
		"Seating Capacity": 5,
		"Body Type": "Sedan",
		"Transmission Type": "Automatic"
	},
	{
		"Car Name": "Toyota Corolla Altis",
		"Image": "toyota_corolla_altis.jpg",
		"Fuel Type": "Petrol",
		"Fuel Tank Capacity": 55,
		"Seating Capacity": 5,
		"Body Type": "Sedan",
		"Transmission Type": "Manual"
	},
	{
		"Car Name": "Toyota Corolla Sedan 2012",
		"Image": "07375.jpg",
		"Fuel Type": "Gas",
		"Fuel Tank Capacity": 50,
		"Seating Capacity": 5,
		"Body Type": "Sedan",
		"Transmission Type": "Automatic"
	},
	{
		"Car Name": "Toyota Etios Liva",
		"Image": "toyota_etios_liva.jpg",
		"Fuel Type": "Petrol",
		"Fuel Tank Capacity": 45,
		"Seating Capacity": 5,
		"Body Type": "Hatchback",
		"Transmission Type": "Manual"
	},
	{
		"Car Name": "Toyota Fortuner",
		"Image": "toyota_fortuner.jpg",
		"Fuel Type": "Diesel",
		"Fuel Tank Capacity": 80,
		"Seating Capacity": 7,
		"Body Type": "SUV",
		"Transmission Type": "Automatic"
	},
	{
		"Car Name": "Toyota Innova",
		"Image": "toyota_innova.jpg",
		"Fuel Type": "Diesel",
		"Fuel Tank Capacity": 55,
		"Seating Capacity": 7,
		"Body Type": "SUV",
		"Transmission Type": "Automatic"
	},
	{
		"Car Name": "Toyota Innova Crysta",
		"Image": "toyota_innova_crysta.jpg",
		"Fuel Type": "Diesel",
		"Fuel Tank Capacity": 55,
		"Seating Capacity": 7,
		"Body Type": "SUV",
		"Transmission Type": "Automatic"
	},
	{
		"Car Name": "Toyota Sequoia SUV 2012",
		"Image": "00045.jpg",
		"Fuel Type": "Gas",
		"Fuel Tank Capacity": 100,
		"Seating Capacity": 8,
		"Body Type": "SUV",
		"Transmission Type": "Automatic"
	},
	{
		"Car Name": "Volkswagen Ameo",
		"Image": "volkswagen_ameo.jpg",
		"Fuel Type": "Petrol",
		"Fuel Tank Capacity": 45,
		"Seating Capacity": 5,
		"Body Type": "Sedan",
		"Transmission Type": "Manual"
	},
	{
		"Car Name": "Volkswagen Beetle Hatchback 2012",
		"Image": "01997.jpg",
		"Fuel Type": "Gas",
		"Fuel Tank Capacity": 55,
		"Seating Capacity": 4,
		"Body Type": "Hatchback / Coupe",
		"Transmission Type": "Automatic"
	},
	{
		"Car Name": "Volkswagen Golf Hatchback 1991",
		"Image": "03300.jpg",
		"Fuel Type": "Gas",
		"Fuel Tank Capacity": 55,
		"Seating Capacity": 5,
		"Body Type": "Hatchback",
		"Transmission Type": "Manual"
	},
	{
		"Car Name": "Volkswagen Golf Hatchback 2012",
		"Image": "00250.jpg",
		"Fuel Type": "Gas",
		"Fuel Tank Capacity": 55,
		"Seating Capacity": 5,
		"Body Type": "Hatchback",
		"Transmission Type": "Automatic"
	},
	{
		"Car Name": "Volkswagen Jetta",
		"Image": "volkswagen_jetta.jpg",
		"Fuel Type": "Petrol",
		"Fuel Tank Capacity": 55,
		"Seating Capacity": 5,
		"Body Type": "Sedan",
		"Transmission Type": "Manual"
	},
	{
		"Car Name": "Volkswagen Polo",
		"Image": "volkswagen_polo.jpg",
		"Fuel Type": "Petrol",
		"Fuel Tank Capacity": 45,
		"Seating Capacity": 5,
		"Body Type": "Hatchback",
		"Transmission Type": "Automatic"
	},
	{
		"Car Name": "Volkswagen Vento",
		"Image": "volkswagen_vento.jpg",
		"Fuel Type": "Petrol",
		"Fuel Tank Capacity": 55,
		"Seating Capacity": 5,
		"Body Type": "Sedan",
		"Transmission Type": "Automatic"
	},
	{
		"Car Name": "Volvo 240 Sedan 1993",
		"Image": "02051.jpg",
		"Fuel Type": "Gas",
		"Fuel Tank Capacity": 60,
		"Seating Capacity": 5,
		"Body Type": "Sedan",
		"Transmission Type": "Manual"
	},
	{
		"Car Name": "Volvo C30 Hatchback 2012",
		"Image": "03114.jpg",
		"Fuel Type": "Gas",
		"Fuel Tank Capacity": 61,
		"Seating Capacity": 4,
		"Body Type": "Hatchback",
		"Transmission Type": "Automatic / Manual"
	},
	{
		"Car Name": "Volvo XC90 SUV 2007",
		"Image": "01513.jpg",
		"Fuel Type": "Gas",
		"Fuel Tank Capacity": 80,
		"Seating Capacity": "5 to 7",
		"Body Type": "SUV",
		"Transmission Type": "Automatic"
	},
	{
		"Car Name": "smart fortwo Convertible 2012",
		"Image": "04970.jpg",
		"Fuel Type": "Gas",
		"Fuel Tank Capacity": 33,
		"Seating Capacity": 2,
		"Body Type": "Convertible",
		"Transmission Type": "Automatic / Manual"
	}
]
